setup.py
distributions_lowe/Binomialdistribution.py
distributions_lowe/Gaussiandistribution.py
distributions_lowe/Generaldistribution.py
distributions_lowe/__init__.py
distributions_lowe.egg-info/PKG-INFO
distributions_lowe.egg-info/SOURCES.txt
distributions_lowe.egg-info/dependency_links.txt
distributions_lowe.egg-info/not-zip-safe
distributions_lowe.egg-info/top_level.txt