Metadata-Version: 1.0
Name: distributions-lowe
Version: 0.2
Summary: Gaussian and Binomial distributions
Home-page: UNKNOWN
Author: Brandon Lowe
Author-email: UNKNOWN
License: UNKNOWN
Platform: UNKNOWN
